docs_crawler/__init__.py
docs_crawler/cache.py
docs_crawler/cli.py
docs_crawler/config.py
docs_crawler/crawler.py
docs_crawler-0.3.0.dist-info/METADATA
docs_crawler-0.3.0.dist-info/WHEEL
docs_crawler-0.3.0.dist-info/entry_points.txt
docs_crawler-0.3.0.dist-info/licenses/LICENSE
docs_crawler-0.3.0.dist-info/RECORD
