Metadata-Version: 2.4
Name: docs-crawler
Version: 0.3.0
Summary: A documentation crawler that converts web documentation to Markdown format
License: MIT
License-File: LICENSE
Keywords: crawler,documentation,markdown,scraper
Author: nev4rb14su
Requires-Python: >=3.8.1,<4.0.0
Classifier: Development Status :: 3 - Alpha
Classifier: Intended Audience :: Developers
Classifier: License :: OSI Approved :: MIT License
Classifier: Programming Language :: Python :: 3
Classifier: Programming Language :: Python :: 3.9
Classifier: Programming Language :: Python :: 3.10
Classifier: Programming Language :: Python :: 3.11
Classifier: Programming Language :: Python :: 3.12
Classifier: Programming Language :: Python :: 3.13
Classifier: Programming Language :: Python :: 3.14
Classifier: Programming Language :: Python :: 3.8
Requires-Dist: beautifulsoup4 (>=4.12.0,<5.0.0)
Requires-Dist: lxml (>=5.0.0,<6.0.0)
Requires-Dist: markdownify (>=0.11.0,<0.12.0)
Requires-Dist: playwright (>=1.40.0,<2.0.0)
Requires-Dist: pyyaml (>=6.0.0,<7.0.0)
Requires-Dist: requests (>=2.31.0,<3.0.0)
Requires-Dist: tqdm (>=4.66.0,<5.0.0)
Project-URL: Homepage, https://github.com/neverbiasu/docs-crawler
